certbot_plugin_dns_loopia.py
loopia_api.py
certbot_plugin_dns_loopia-0.1.0.dist-info/licenses/LICENSE
certbot_plugin_dns_loopia-0.1.0.dist-info/METADATA
certbot_plugin_dns_loopia-0.1.0.dist-info/WHEEL
certbot_plugin_dns_loopia-0.1.0.dist-info/entry_points.txt
certbot_plugin_dns_loopia-0.1.0.dist-info/top_level.txt
certbot_plugin_dns_loopia-0.1.0.dist-info/RECORD
