Metadata-Version: 2.4
Name: certbot-plugin-dns-loopia
Version: 0.1.0
Summary: A Certbot plugin for certificate renewal using Loopia DNS
Home-page: https://github.com/aigr20/certbot-plugin-dns-loopia
Author: Wilhelm Gren
Author-email: wilhelmgren@outlook.com
License-Expression: MIT
Project-URL: Repository, https://github.com/aigr20/certbot-plugin-dns-loopia
License-File: LICENSE
Dynamic: author
Dynamic: author-email
Dynamic: home-page
Dynamic: license-file
